armar/__init__.py
armar/urdf_provider.py
armar/description/meshes/armar4/collision/arml_elb1_joint.stl
armar/description/meshes/armar4/collision/arml_elb2_joint.stl
armar/description/meshes/armar4/collision/arml_sho1_joint.stl
armar/description/meshes/armar4/collision/arml_sho2_joint.stl
armar/description/meshes/armar4/collision/arml_sho3_joint.stl
armar/description/meshes/armar4/collision/arml_sho4_joint.stl
armar/description/meshes/armar4/collision/arml_wri2_joint.stl
armar/description/meshes/armar4/collision/armr_elb1_joint.stl
armar/description/meshes/armar4/collision/armr_elb2_joint.stl
armar/description/meshes/armar4/collision/armr_sho1_joint.stl
armar/description/meshes/armar4/collision/armr_sho2_joint.stl
armar/description/meshes/armar4/collision/armr_sho3_joint.stl
armar/description/meshes/armar4/collision/armr_sho4_joint.stl
armar/description/meshes/armar4/collision/armr_wri2_joint.stl
armar/description/meshes/armar4/collision/eyel_2_joint.stl
armar/description/meshes/armar4/collision/eyer_2_joint.stl
armar/description/meshes/armar4/collision/handl_finger_index1_joint.stl
armar/description/meshes/armar4/collision/handl_finger_index2_joint.stl
armar/description/meshes/armar4/collision/handl_finger_middle1_joint.stl
armar/description/meshes/armar4/collision/handl_finger_middle2_joint.stl
armar/description/meshes/armar4/collision/handl_finger_pinky1_joint.stl
armar/description/meshes/armar4/collision/handl_finger_pinky2_joint.stl
armar/description/meshes/armar4/collision/handl_finger_ring1_joint.stl
armar/description/meshes/armar4/collision/handl_finger_ring2_joint.stl
armar/description/meshes/armar4/collision/handl_finger_thumb1_joint.stl
armar/description/meshes/armar4/collision/handl_finger_thumb2_joint.stl
armar/description/meshes/armar4/collision/handl_finger_thumb3_joint.stl
armar/description/meshes/armar4/collision/handl_static.obj
armar/description/meshes/armar4/collision/handr_finger_index1_joint.stl
armar-1.1.0.dist-info/LICENSE
armar-1.1.0.dist-info/METADATA
armar-1.1.0.dist-info/WHEEL
armar-1.1.0.dist-info/top_level.txt
armar-1.1.0.dist-info/RECORD
