Metadata-Version: 2.1
Name: armar
Version: 1.1.0
Summary: URDF Files for Humanoid Robots of the ARMAR Family
Home-page: https://github.com/translearn/armar-urdf
Author: translearn
Author-email: jonas.kiemel@kit.edu
License: CC BY-NC 4.0
Platform: UNKNOWN
Classifier: Intended Audience :: Developers
Classifier: Programming Language :: Python :: 3.6
Classifier: Programming Language :: Python :: 3.7
Classifier: Programming Language :: Python :: 3.8
Classifier: Programming Language :: Python :: 3.9
Requires-Python: >=3.5
